spectra_torch/__init__.py
spectra_torch/base.py
spectra_torch-0.4.0.dist-info/METADATA
spectra_torch-0.4.0.dist-info/WHEEL
spectra_torch-0.4.0.dist-info/top_level.txt
spectra_torch-0.4.0.dist-info/RECORD
