Metadata-Version: 2.1
Name: spectra-torch
Version: 0.4.0
Summary: Spectra Extraction based on PyTorch
Home-page: https://github.com/mechanicalsea/spectra
Author: WangRui
Author-email: rwang@tongji.edu.cn
License: UNKNOWN
Platform: UNKNOWN
Classifier: Programming Language :: Python :: 3.7
Requires-Dist: torch
Requires-Dist: torchaudio
